flexpoolapi/__init__.py
flexpoolapi/exceptions.py
flexpoolapi/minerapi.py
flexpoolapi/poolapi.py
flexpoolapi/shared.py
flexpoolapi/utils.py
flexpoolapi_v2-2.2.4.post7.dist-info/LICENSE
flexpoolapi_v2-2.2.4.post7.dist-info/METADATA
flexpoolapi_v2-2.2.4.post7.dist-info/WHEEL
flexpoolapi_v2-2.2.4.post7.dist-info/top_level.txt
flexpoolapi_v2-2.2.4.post7.dist-info/RECORD
