Metadata-Version: 2.1
Name: flexpoolapi-v2
Version: 2.2.4.post7
Summary: 🐍 Pythonic wrapper for Flexpool API v2
Home-page: https://github.com/nekusu/py-flexpoolapi-v2
Author: nekusu
Author-email: nekusu.dev@gmail.com
License: MIT
Platform: UNKNOWN
Classifier: Programming Language :: Python :: 3
Classifier: License :: OSI Approved :: MIT License
Classifier: Operating System :: OS Independent
Requires-Python: >=3.6
Requires-Dist: requests
Requires-Dist: si-prefix
